<?xml version = '1.0'?>
<species>
	<cross num="1">
		<predicted>Centrarchidae</predicted>
		<r2>0.8093237300</r2>
		<pVal>0.0000003766</pVal>
		<df>16</df>
		<intercept>1.2627986920</intercept>
		<slope>0.7679220950</slope>
		<xAvg>1.7716788260</xAvg>
		<xMin>-2.8471886490</xMin>
		<xMax>4.2174839440</xMax>
		<Sxx>65.9366440500</Sxx>
		<MSE>0.5725528170</MSE>
		<t90CI>1.746</t90CI>
		<t95CI>2.12</t95CI>
		<t99CI>2.921</t99CI>
		<Bootstrap>66.66666667</Bootstrap>
		<taxDist>6</taxDist>
	</cross>
	<cross num="2">
		<predicted>Chironomidae</predicted>
		<r2>0.7775393020</r2>
		<pVal>0.0001486360</pVal>
		<df>10</df>
		<intercept>0.6006490520</intercept>
		<slope>0.8023936970</slope>
		<xAvg>1.6649529550</xAvg>
		<xMin>-1.4948500220</xMin>
		<xMax>3.6232492900</xMax>
		<Sxx>32.2419595100</Sxx>
		<MSE>0.5939192350</MSE>
		<t90CI>1.812</t90CI>
		<t95CI>2.228</t95CI>
		<t99CI>3.169</t99CI>
		<Bootstrap>75</Bootstrap>
		<taxDist>5</taxDist>
	</cross>
	<cross num="3">
		<predicted>Cyprinidae</predicted>
		<r2>0.8870402690</r2>
		<pVal>0.0000148611</pVal>
		<df>9</df>
		<intercept>1.8926280850</intercept>
		<slope>0.7475764500</slope>
		<xAvg>1.5758908330</xAvg>
		<xMin>-1.4948500220</xMin>
		<xMax>3.8162413000</xMax>
		<Sxx>35.5804208100</Sxx>
		<MSE>0.2813585440</MSE>
		<t90CI>1.833</t90CI>
		<t95CI>2.262</t95CI>
		<t99CI>3.25</t99CI>
		<Bootstrap>72.72727273</Bootstrap>
		<taxDist>6</taxDist>
	</cross>
	<cross num="4">
		<predicted>Cyprinodontidae</predicted>
		<r2>0.9084705080</r2>
		<pVal>0.0468628070</pVal>
		<df>2</df>
		<intercept>1.8489385000</intercept>
		<slope>0.5314208140</slope>
		<xAvg>1.6251654440</xAvg>
		<xMin>-0.7695510790</xMin>
		<xMax>2.9637878270</xMax>
		<Sxx>9.1263757590</Sxx>
		<MSE>0.1298361680</MSE>
		<t90CI>2.92</t90CI>
		<t95CI>4.303</t95CI>
		<t99CI>9.925</t99CI>
		<Bootstrap>75</Bootstrap>
		<taxDist>6</taxDist>
	</cross>
	<cross num="5">
		<predicted>Daphniidae</predicted>
		<r2>0.6920248470</r2>
		<pVal>0.0000644549</pVal>
		<df>14</df>
		<intercept>0.3788369400</intercept>
		<slope>0.8185664130</slope>
		<xAvg>2.1263489850</xAvg>
		<xMin>-2.8471886490</xMin>
		<xMax>4.2174839440</xMax>
		<Sxx>46.5993201400</Sxx>
		<MSE>0.9925522500</MSE>
		<t90CI>1.761</t90CI>
		<t95CI>2.145</t95CI>
		<t99CI>2.977</t99CI>
		<Bootstrap>43.75</Bootstrap>
		<taxDist>5</taxDist>
	</cross>
	<cross num="6">
		<predicted>Gammaridae</predicted>
		<r2>0.9526722270</r2>
		<pVal>0.0044334810</pVal>
		<df>3</df>
		<intercept>0.1922912360</intercept>
		<slope>0.9828851720</slope>
		<xAvg>1.3480646030</xAvg>
		<xMin>-0.7695510790</xMin>
		<xMax>3.6111183200</xMax>
		<Sxx>10.1961349800</Sxx>
		<MSE>0.1631144570</MSE>
		<t90CI>2.353</t90CI>
		<t95CI>3.182</t95CI>
		<t99CI>5.841</t99CI>
		<Bootstrap>100</Bootstrap>
		<taxDist>2</taxDist>
	</cross>
	<cross num="7">
		<predicted>Salmonidae</predicted>
		<r2>0.7459447990</r2>
		<pVal>0.0000038750</pVal>
		<df>16</df>
		<intercept>1.3206442530</intercept>
		<slope>0.6964230820</slope>
		<xAvg>1.7698219510</xAvg>
		<xMin>-2.8471886490</xMin>
		<xMax>4.2174839440</xMax>
		<Sxx>65.8617064700</Sxx>
		<MSE>0.6799558420</MSE>
		<t90CI>1.746</t90CI>
		<t95CI>2.12</t95CI>
		<t99CI>2.921</t99CI>
		<Bootstrap>50</Bootstrap>
		<taxDist>6</taxDist>
	</cross>
</species>
